tpeai/.ipynb_checkpoints/__init__-checkpoint.py
tpeai/__init__.py
tpeai-0.2.0.dist-info/METADATA
tpeai-0.2.0.dist-info/WHEEL
tpeai-0.2.0.dist-info/RECORD
