Metadata-Version: 2.1
Name: tpeai
Version: 0.2.0
Summary: A Python package to differentiate between tuberculous and non-tuberculous pleural effusion using ChatGPT-4 with biochemistry and blood cell analysis data.
Author: Cj Yan
Author-email: yanchangjian2019@126.com
Requires-Python: >=3.9,<4.0
Classifier: Programming Language :: Python :: 3
Classifier: Programming Language :: Python :: 3.9
Classifier: Programming Language :: Python :: 3.10
Classifier: Programming Language :: Python :: 3.11
Classifier: Programming Language :: Python :: 3.12
Requires-Dist: openai (>=1.30.3,<2.0.0)
Requires-Dist: pandas (>=2.2.2,<3.0.0)
